mtf2json/__init__.py
mtf2json/armor.py
mtf2json/cli.py
mtf2json/critical_slots.py
mtf2json/data/__init__.py
mtf2json/data/equipment.csv
mtf2json/data/physical_weapons.csv
mtf2json/data/weapons.csv
mtf2json/engine.py
mtf2json/equipment.py
mtf2json/error.py
mtf2json/fluff.py
mtf2json/heat_sinks.py
mtf2json/items.py
mtf2json/mtf2json.py
mtf2json/py.typed
mtf2json/quirks.py
mtf2json/rules_level.py
mtf2json/structure.py
mtf2json/weapons.py
mtf2json-0.2.7.dist-info/LICENSE
mtf2json-0.2.7.dist-info/METADATA
mtf2json-0.2.7.dist-info/WHEEL
mtf2json-0.2.7.dist-info/entry_points.txt
mtf2json-0.2.7.dist-info/RECORD
