Metadata-Version: 2.1
Name: mtf2json
Version: 0.2.7
Summary: Convert the MegaMek MTF format to JSON.
Home-page: https://github.com/juk0de/mtf2json
License: GPL-3.0-or-later
Keywords: MTF,JSON,MegaMek,BattleTech
Author: juk0de
Author-email: juk0de@kadidlo.de
Requires-Python: >=3.12,<4.0
Classifier: Development Status :: 3 - Alpha
Classifier: License :: OSI Approved :: GNU General Public License v3 or later (GPLv3+)
Classifier: Programming Language :: Python :: 3
Classifier: Programming Language :: Python :: 3.12
Requires-Dist: pandas (>=2.2.3,<3.0.0)
Project-URL: Repository, https://github.com/juk0de/mtf2json
